{"name":"build-javascript","namedChunkGroups":{"app":{"name":"app","assets":[{"name":"webpack-runtime-ce19161fab101c46d8de.js","size":3886},{"name":"framework-a4e155cd0476dc1ca208.js","size":140747},{"name":"styles.5e06ce975d9cfa027185.css","size":30128},{"name":"app-1af58def7c793ab9bdcb.js","size":97433}],"filteredAssets":0,"assetsSize":272194,"filteredAuxiliaryAssets":3,"auxiliaryAssetsSize":732349},"component---src-pages-404-js":{"name":"component---src-pages-404-js","assets":[{"name":"component---src-pages-404-js-78e4980f79da19f0c568.js","size":13255}],"filteredAssets":0,"assetsSize":13255,"filteredAuxiliaryAssets":1,"auxiliaryAssetsSize":23916},"component---src-pages-index-js":{"name":"component---src-pages-index-js","assets":[{"name":"component---src-pages-index-js-d425f12753381eb6a465.js","size":84728}],"filteredAssets":0,"assetsSize":84728,"filteredAuxiliaryAssets":7,"auxiliaryAssetsSize":14471773},"component---src-pages-kontakt-js":{"name":"component---src-pages-kontakt-js","assets":[{"name":"component---src-pages-kontakt-js-1b8f8d5bb53c3671e30d.js","size":13234}],"filteredAssets":0,"assetsSize":13234,"filteredAuxiliaryAssets":1,"auxiliaryAssetsSize":23923}},"assetsByChunkName":{"app":["webpack-runtime-ce19161fab101c46d8de.js","framework-a4e155cd0476dc1ca208.js","styles.5e06ce975d9cfa027185.css","app-1af58def7c793ab9bdcb.js"],"component---src-pages-404-js":["component---src-pages-404-js-78e4980f79da19f0c568.js"],"component---src-pages-index-js":["component---src-pages-index-js-d425f12753381eb6a465.js"],"component---src-pages-kontakt-js":["component---src-pages-kontakt-js-1b8f8d5bb53c3671e30d.js"]},"childAssetsByChunkName":{}}